__init__.py
lw.dll
lwplugin.py
lwplugin-0.0.5.dist-info/METADATA
lwplugin-0.0.5.dist-info/WHEEL
lwplugin-0.0.5.dist-info/top_level.txt
lwplugin-0.0.5.dist-info/RECORD
