Metadata-Version: 2.1
Name: lwplugin
Version: 0.0.5
Summary: lw plugin wapper
Home-page: UNKNOWN
Author: linx
Author-email: modemlxsg@gmail.com
License: UNKNOWN
Platform: UNKNOWN
Classifier: Programming Language :: Python :: 3
Classifier: Operating System :: Microsoft :: Windows
Requires-Python: >= 3.7
Requires-Dist: comtypes (>=1.1.7)
